{
  "project_info": {
    "project_number": "532698549810",
    "firebase_url": "https://notes-ec3c2.firebaseio.com",
    "project_id": "notes-ec3c2",
    "storage_bucket": "notes-ec3c2.appspot.com"
  },
  "client": [
    {
      "client_info": {
        "mobilesdk_app_id": "1:532698549810:android:ef716c5a95efba53",
        "android_client_info": {
          "package_name": "pl.codeinprogress.notes"
        }
      },
      "oauth_client": [
        {
          "client_id": "532698549810-ntb5u6hs7laj03rgrcercop4c0kbsh8t.apps.googleusercontent.com",
          "client_type": 3
        }
      ],
      "api_key": [
        {
          "current_key": "AIzaSyA4ag1smkleM7IONFF7VJOBZExKXRi3qas"
        }
      ],
      "services": {
        "analytics_service": {
          "status": 1
        },
        "appinvite_service": {
          "status": 1,
          "other_platform_oauth_client": []
        },
        "ads_service": {
          "status": 2
        }
      }
    }
  ],
  "configuration_version": "1"
}